dproc/__init__.py
dproc/_nbdev.py
dproc/core.py
dproc-0.0.2.dist-info/LICENSE
dproc-0.0.2.dist-info/METADATA
dproc-0.0.2.dist-info/WHEEL
dproc-0.0.2.dist-info/entry_points.txt
dproc-0.0.2.dist-info/top_level.txt
dproc-0.0.2.dist-info/RECORD
