Metadata-Version: 2.1
Name: dproc
Version: 0.0.2
Summary: A convenient data flow to preprocess data using metadata.
Home-page: https://github.com/tkanngiesser/dproc
Author: Tino Kanngiesser
Author-email: tinokanngiesser@gmail.com
License: Apache Software License 2.0
Keywords: meta data flow pipeline preprocessing
Platform: UNKNOWN
Classifier: Development Status :: 3 - Alpha
Classifier: Intended Audience :: Developers
Classifier: License :: OSI Approved :: Apache Software License
Classifier: Natural Language :: English
Classifier: Programming Language :: Python :: 3.6
Classifier: Programming Language :: Python :: 3.7
Classifier: Programming Language :: Python :: 3.8
Requires-Python: >=3.6
Requires-Dist: pandas-profiling
Requires-Dist: pandas-flavor
Requires-Dist: dataclasses
